{
  "$schema": "https://ui.shadcn.com/schema/registry-item.json",
  "name": "uiable-message-scroller-load-history",
  "title": "Loading Earlier Messages",
  "description": "Message Scroller Load History variant for message-scroller.",
  "registryDependencies": [
    "message-scroller"
  ],
  "files": [
    {
      "path": "src/components/uiable/message-scroller/message-scroller-load-history.tsx",
      "content": "\"use client\"\r\n\r\nimport { useCallback, useState } from \"react\"\r\n// assets\r\nimport { RotateCwIcon } from \"lucide-react\"\r\n\r\n// third party\r\nimport { toast } from \"sonner\"\r\n\r\n// shadcn\r\nimport { Button } from \"@/components/ui/button\"\r\nimport {\r\n  Card,\r\n  CardAction,\r\n  CardContent,\r\n  CardDescription,\r\n  CardFooter,\r\n  CardHeader,\r\n  CardTitle,\r\n} from \"@/components/ui/card\"\r\nimport {\r\n  MessageScroller,\r\n  MessageScrollerButton,\r\n  MessageScrollerContent,\r\n  MessageScrollerProvider,\r\n  MessageScrollerViewport,\r\n} from \"@/components/ui/message-scroller\"\r\nimport {\r\n  Tooltip,\r\n  TooltipContent,\r\n  TooltipTrigger,\r\n} from \"@/components/ui/tooltip\"\r\n// projects\r\nimport { MessageAnimated } from \"@/components/message-animated\"\r\n\r\ntype ChatMessage = {\r\n  id: string\r\n  role: \"assistant\" | \"user\"\r\n  text: string\r\n}\r\n\r\nconst initialMessages: ChatMessage[] = [\r\n  {\r\n    id: \"load-history-4\",\r\n    role: \"assistant\",\r\n    text: \"Only the export queue worker changed. The deploy moved large CSV jobs onto the shared retry policy, which made each failed attempt hold a worker slot longer than before.\",\r\n  },\r\n  {\r\n    id: \"load-history-5\",\r\n    role: \"user\",\r\n    text: \"Do we need to roll back?\",\r\n  },\r\n  {\r\n    id: \"load-history-6\",\r\n    role: \"assistant\",\r\n    text: \"Not yet. Queue depth is recovering after we reduced retry concurrency, and the oldest pending job is now under five minutes old.\",\r\n  },\r\n]\r\n\r\nconst earlierMessages: ChatMessage[] = [\r\n  {\r\n    id: \"load-history-1\",\r\n    role: \"assistant\",\r\n    text: \"The app deploy did not include checkout, pricing, or billing API changes.\",\r\n  },\r\n  {\r\n    id: \"load-history-2\",\r\n    role: \"assistant\",\r\n    text: \"Do we need to roll back? This is a support thread with several failed export jobs, but the internal queue recovery looks stable.\",\r\n  },\r\n  {\r\n    id: \"load-history-3\",\r\n    role: \"assistant\",\r\n    text: \"Keep rollback ready if the queue starts climbing again, but the current trend points toward recovery.\",\r\n  },\r\n]\r\n\r\n//  ------------------------------ | MESSAGE SCROLLER - LOAD HISTORY | ------------------------------  //\r\n\r\nexport function MessageScrollerLoadHistory() {\r\n  const [messages, setMessages] = useState(initialMessages)\r\n  const [historyLoaded, setHistoryLoaded] = useState(false)\r\n\r\n  const loadEarlierMessages = useCallback(() => {\r\n    if (historyLoaded) {\r\n      return\r\n    }\r\n\r\n    setMessages((current) => [...earlierMessages, ...current])\r\n    setHistoryLoaded(true)\r\n    toast.success(\"History loaded\", {\r\n      description: \"Scroll up to see earlier messages.\",\r\n    })\r\n  }, [historyLoaded])\r\n\r\n  const resetDemo = useCallback(() => {\r\n    setMessages(initialMessages)\r\n    setHistoryLoaded(false)\r\n  }, [])\r\n\r\n  return (\r\n    <MessageScrollerProvider defaultScrollPosition=\"end\" scrollMargin={24}>\r\n      <div className=\"relative flex flex-col gap-4\">\r\n        <Card className=\"mx-auto mb-0 flex h-140 w-full max-w-sm flex-col gap-0 overflow-hidden\">\r\n          <CardHeader className=\"grid grid-cols-[1fr_auto] gap-x-4 border-b\">\r\n            <div className=\"flex flex-col gap-1\">\r\n              <CardTitle>Load History</CardTitle>\r\n              <CardDescription>\r\n                Prepended messages keep your place.\r\n              </CardDescription>\r\n            </div>\r\n            <CardAction>\r\n              <Tooltip>\r\n                <TooltipTrigger\r\n                  render={\r\n                    <Button\r\n                      type=\"button\"\r\n                      variant=\"outline\"\r\n                      size=\"icon\"\r\n                      aria-label=\"Reset load history demo\"\r\n                      onClick={resetDemo}\r\n                    >\r\n                      <RotateCwIcon />\r\n                    </Button>\r\n                  }\r\n                />\r\n                <TooltipContent>Reset</TooltipContent>\r\n              </Tooltip>\r\n            </CardAction>\r\n          </CardHeader>\r\n          <CardContent className=\"min-h-0 flex-1 overflow-hidden p-0 pt-3\">\r\n            <MessageScroller>\r\n              <MessageScrollerViewport className=\"px-4\">\r\n                <MessageScrollerContent className=\"p-(--card-spacing)\">\r\n                  {messages.map((message) => (\r\n                    <MessageAnimated\r\n                      key={message.id}\r\n                      message={message}\r\n                      showAvatar={false}\r\n                    />\r\n                  ))}\r\n                </MessageScrollerContent>\r\n              </MessageScrollerViewport>\r\n              <MessageScrollerButton />\r\n            </MessageScroller>\r\n          </CardContent>\r\n          <CardFooter className=\"flex flex-col gap-2 border-t px-3 py-3\">\r\n            <Button\r\n              type=\"button\"\r\n              disabled={historyLoaded}\r\n              onClick={loadEarlierMessages}\r\n              className=\"w-full\"\r\n            >\r\n              {historyLoaded ? \"History Loaded\" : \"Load History\"}\r\n            </Button>\r\n            <p className=\"text-xs text-muted-foreground\">\r\n              Restore earlier messages while keeping your place.\r\n            </p>\r\n          </CardFooter>\r\n        </Card>\r\n      </div>\r\n    </MessageScrollerProvider>\r\n  )\r\n}\r\n",
      "type": "registry:component",
      "target": "@components/uiable/message-scroller/message-scroller-load-history.tsx"
    }
  ],
  "categories": [
    "message-scroller"
  ],
  "type": "registry:ui"
}