{
  "$schema": "https://ui.shadcn.com/schema/registry-item.json",
  "name": "uiable-button-render",
  "title": "Render Button",
  "description": "Button Render variant for button.",
  "registryDependencies": [
    "button"
  ],
  "files": [
    {
      "path": "src/components/uiable/button/button-render.tsx",
      "content": "// shadcn\r\nimport { Button } from \"@/components/ui/button\";\r\n\r\n//  ------------------------------ | BUTTON RENDER | ------------------------------  //\r\n\r\nexport default function ButtonRender() {\r\n  return (\r\n    <Button nativeButton={false} render={<a href=\"#\" />}>\r\n      Login\r\n    </Button>\r\n  );\r\n}\r\n",
      "type": "registry:component",
      "target": "@components/uiable/button/button-render.tsx"
    }
  ],
  "categories": [
    "button"
  ],
  "type": "registry:ui"
}